datahelper/__init__.py
datahelper/dynamodb/__init__.py
datahelper/dynamodb/dynamodb_data_helper.py
datahelper/dynamodb/learningdb_dev_data_helper.py
datahelper/mongodb/__init__.py
datahelper/mongodb/dataplatform_dev_data_helper.py
datahelper/mongodb/mongodb_data_helper.py
datahelper/mongodb/data_platform_dev/__init__.py
datahelper/mongodb/data_platform_dev/find.py
datahelper/s3/__init__.py
datahelper/s3/learningdb_dev_data_helper.py
datahelper/s3/s3_data_helper.py
datahelper/s3/ml_learning_dev/__init__.py
datahelper/s3/ml_learning_dev/s3_path_helper.py
datahelper/url/__init__.py
datahelper/url/url_helper.py
etl/__init__.py
etl/etl.py
sync/__init__.py
sync/table_syncer.py
mlcore-0.1.0.dev9.dist-info/METADATA
mlcore-0.1.0.dev9.dist-info/WHEEL
mlcore-0.1.0.dev9.dist-info/top_level.txt
mlcore-0.1.0.dev9.dist-info/RECORD
